packagesrohan/__init__.py
pachagesrohan-0.1.dist-info/Licence.txt.txt
pachagesrohan-0.1.dist-info/METADATA
pachagesrohan-0.1.dist-info/WHEEL
pachagesrohan-0.1.dist-info/top_level.txt
pachagesrohan-0.1.dist-info/RECORD
