Metadata-Version: 2.1
Name: pachagesrohan
Version: 0.1
Summary: This is sample package.
Home-page: UNKNOWN
Author: Rohan
Author-email: UNKNOWN
License: UNKNOWN
Platform: UNKNOWN
